.coveragerc
.gitignore
.gitlab-ci.yml
ACKNOWLEDGEMENTS
CONTRIBUTING.rst
Dockerfile
LICENSE
MANIFEST.in
Makefile
Readme.rst
Singularity
codemeta.json
pytest.ini
requirements.txt
requirements_dev.txt
setup.cfg
setup.py
.gitlab/issue_templates/Bug.md
.gitlab/issue_templates/Feature.md
docs/CONTRIBUTING.rst
docs/Makefile
docs/conf.py
docs/example_models.rst
docs/example_on_toy_data.rst
docs/index.rst
docs/learning_rate.rst
docs/modifiers.rst
docs/python_overview.rst
docs/quick_start.rst
docs/toml_files.rst
docs/_static/.gitkeep
docs/_static/orcanet_logo.png
docs/_static/orcanet_logo.svg
docs/_static/orcanet_logo_larger_margin.png
docs/_static/orcanet_logo_larger_margin.svg
docs/_static/orcanet_logo_larger_margin_lowres.jpg
docs/_static/orcanet_wide_transparent_black.png
docs/_static/orcanet_wide_transparent_black.svg
docs/_static/orcanet_wide_transparent_white.png
docs/_static/orcanet_wide_transparent_white.svg
docs/_static/style.css
docs/_templates/.gitkeep
docs/_templates/layout.html
examples/config.toml
examples/learning_rate.csv
examples/list.toml
examples/full_example/__init__.py
examples/full_example/example_list.toml
examples/full_example/full_example.py
examples/model_files/cnn.toml
examples/model_files/explanation.toml
examples/model_files/graph_disjoint_edgeconv.toml
examples/model_files/inception.toml
examples/model_files/lstm.toml
examples/model_files/resnet.toml
orcanet/__init__.py
orcanet/__version__.py
orcanet/backend.py
orcanet/core.py
orcanet/h5_generator.py
orcanet/history.py
orcanet/in_out.py
orcanet/logging.py
orcanet/misc.py
orcanet/model_builder.py
orcanet/parser.py
orcanet/version.txt
orcanet.egg-info/PKG-INFO
orcanet.egg-info/SOURCES.txt
orcanet.egg-info/dependency_links.txt
orcanet.egg-info/entry_points.txt
orcanet.egg-info/requires.txt
orcanet.egg-info/top_level.txt
orcanet/builder_util/__init__.py
orcanet/builder_util/builders.py
orcanet/builder_util/layer_blocks.py
orcanet/lib/__init__.py
orcanet/lib/dataset_modifiers.py
orcanet/lib/label_modifiers.py
orcanet/lib/losses.py
orcanet/lib/sample_modifiers.py
orcanet/tests/__init__.py
orcanet/tests/test_backend.py
orcanet/tests/test_builders.py
orcanet/tests/test_core.py
