Metadata-Version: 2.1
Name: orcanet
Version: 1.0.3
Summary: Runs Neural Networks for usage in the KM3NeT project
Home-page: https://git.km3net.de/ml/OrcaNet
Author: Michael Moser, Stefan Reck
Author-email: stefan.reck@fau.de, mmoser@km3net.de, michael.m.moser@fau.de
License: AGPL
Platform: UNKNOWN
Classifier: Development Status :: 3 - Alpha
Classifier: Intended Audience :: Developers
Classifier: Intended Audience :: Science/Research
Classifier: Programming Language :: Python
License-File: LICENSE
